timeseriesfcst/__init__.py
timeseriesfcst/basic_model.py
timeseriesfcst/decomposition.py
timeseriesfcst/evaluation.py
timeseriesfcst/feature_engineering.py
timeseriesfcst/feature_selection.py
timeseriesfcst/lstm.py
timeseriesfcst/preprocessing.py
timeseriesfcst-0.1.4.dist-info/LICENSE
timeseriesfcst-0.1.4.dist-info/METADATA
timeseriesfcst-0.1.4.dist-info/WHEEL
timeseriesfcst-0.1.4.dist-info/top_level.txt
timeseriesfcst-0.1.4.dist-info/RECORD
